pybaseutils/__init__.py
pybaseutils/base64_utils.py
pybaseutils/batch_utils.py
pybaseutils/color_utils.py
pybaseutils/config_utils.py
pybaseutils/coords_utils.py
pybaseutils/data_utils.py
pybaseutils/dict_uils.py
pybaseutils/file_utils.py
pybaseutils/font_utils.py
pybaseutils/geometry_tools.py
pybaseutils/heatmap_utils.py
pybaseutils/http_utils.py
pybaseutils/image_utils.py
pybaseutils/json_utils.py
pybaseutils/log.py
pybaseutils/log_utils.py
pybaseutils/numpy_utils.py
pybaseutils/pandas_utils.py
pybaseutils/plot_utils.py
pybaseutils/setup_config.py
pybaseutils/singleton_utils.py
pybaseutils/text_utils.py
pybaseutils/thread_utils.py
pybaseutils/time_utils.py
pybaseutils/tracemalloc_utils.py
pybaseutils/tracemalloc_utils2.py
pybaseutils/word_utils.py
pybaseutils/worker.py
pybaseutils/yaml_utils.py
pybaseutils/audio/__init__.py
pybaseutils/audio/audio_utils.py
pybaseutils/audio/pyaudio_utils.py
pybaseutils/audio/vad_utils.py
pybaseutils/base/__init__.py
pybaseutils/base/dict_queue.py
pybaseutils/base/list_queue.py
pybaseutils/base/producer_consumer.py
pybaseutils/build_utils/__init__.py
pybaseutils/build_utils/cython_utils.py
pybaseutils/build_utils/pyarmor_utils.py
pybaseutils/cluster/__init__.py
pybaseutils/cluster/kmean.py
pybaseutils/cluster/maxmin_distance.py
pybaseutils/cluster/similarity.py
pybaseutils/converter/__init__.py
pybaseutils/converter/build_coco.py
pybaseutils/converter/build_cvat.py
pybaseutils/converter/build_labelme.py
pybaseutils/converter/build_voc.py
pybaseutils/converter/concat_coco.py
pybaseutils/converter/convert_coco2labelme.py
pybaseutils/converter/convert_coco2voc.py
pybaseutils/converter/convert_cvat2labelme.py
pybaseutils/converter/convert_labelme2coco.py
pybaseutils/converter/convert_labelme2cvat.py
pybaseutils/converter/convert_labelme2labelme.py
pybaseutils/converter/convert_labelme2voc.py
pybaseutils/converter/convert_labelme2yolo.py
pybaseutils/converter/convert_voc2coco.py
pybaseutils/converter/convert_voc2labelme.py
pybaseutils-2.4.7.dist-info/licenses/LICENCE
pybaseutils-2.4.7.dist-info/METADATA
pybaseutils-2.4.7.dist-info/WHEEL
pybaseutils-2.4.7.dist-info/top_level.txt
pybaseutils-2.4.7.dist-info/RECORD
