Metadata-Version: 2.4
Name: pybaseutils
Version: 2.4.7
Summary: pybaseutils
Home-page: https://github.com/PanJinquan/base-utils
Author: PanJinquan
Author-email: 390737991@qq.com
License: MIT
License-File: LICENCE
Dynamic: author
Dynamic: author-email
Dynamic: description
Dynamic: home-page
Dynamic: license
Dynamic: license-file
Dynamic: summary
